{
  "sections": {
    "banner": {
      "type": "main-page-contact",
      "settings": {
        "color_schema": "second_color",
        "banner_top_size": "banner_top_small",
        "banner_bottom_size": "banner_bottom_small",
        "overlay_set": true,
        "text_align": "font_center",
        "headline": "OUR THEME",
        "description": "<p>Thanks for choosing my theme! <\/p><p>This is the information page to introduct my theme! Please read be careful! <\/p><p>Thank you so much! :)<\/p>",
        "text_color": "#6f665d"
      }
    },
    "7df1c7f1-8d90-4871-b3ff-6a194669e723": {
      "type": "section-3column",
      "blocks": {
        "template--15872584614079__7df1c7f1-8d90-4871-b3ff-6a194669e723-1664961825eb37531a-0": {
          "type": "image",
          "settings": {
            "image_round": false,
            "headline": "CUSTOMIZABLE",
            "grid-text": "<p>You are able to select five colors for your brand. customizeable font, Control section padding size, and background color too! <\/p>",
            "textbox_title_align": "font_center",
            "color_box_schema": "fifth_color",
            "grid_header_color_title": "#4b4b4b",
            "grid_color_title": "#4b4b4b",
            "button-url": "",
            "button-text": "",
            "color_button": "second_color",
            "button_color_hover": "button_third_color",
            "border_color": "#6f665d"
          }
        },
        "template--15872584614079__7df1c7f1-8d90-4871-b3ff-6a194669e723-1664961825eb37531a-1": {
          "type": "image",
          "settings": {
            "image_round": false,
            "headline": "15 Featured Sections",
            "grid-text": "<p>You don't need to code. just you can edit your font, size, section size, and font colors. Also, a grid style is available with a selector. <\/p>",
            "textbox_title_align": "font_center",
            "color_box_schema": "fifth_color",
            "grid_header_color_title": "#4b4b4b",
            "grid_color_title": "#4b4b4b",
            "button-url": "",
            "button-text": "",
            "color_button": "second_color",
            "button_color_hover": "button_third_color",
            "border_color": "#6f665d"
          }
        },
        "template--15872584614079__7df1c7f1-8d90-4871-b3ff-6a194669e723-1664961825eb37531a-2": {
          "type": "image",
          "settings": {
            "image_round": false,
            "headline": "MAKE WITH LOVE!",
            "grid-text": "<p>I make shopify themes with love. I try to make the theme beautiful but comfortable for users. Start your online business!<\/p>",
            "textbox_title_align": "font_center",
            "color_box_schema": "fifth_color",
            "grid_header_color_title": "#4b4b4b",
            "grid_color_title": "#4b4b4b",
            "button-url": "",
            "button-text": "",
            "color_button": "second_color",
            "button_color_hover": "button_third_color",
            "border_color": "#6f665d"
          }
        }
      },
      "block_order": [
        "template--15872584614079__7df1c7f1-8d90-4871-b3ff-6a194669e723-1664961825eb37531a-0",
        "template--15872584614079__7df1c7f1-8d90-4871-b3ff-6a194669e723-1664961825eb37531a-1",
        "template--15872584614079__7df1c7f1-8d90-4871-b3ff-6a194669e723-1664961825eb37531a-2"
      ],
      "settings": {
        "color_schema": "background_transparent",
        "padding_top": 4,
        "padding_bottom": 4,
        "headline": "About our theme",
        "text": "",
        "image_onboarding": false,
        "animation_setting": false,
        "button_size": "button_medium",
        "button_round_off": false,
        "grid_style": "three_column",
        "title_align": "font_center",
        "color_title": "#4b4b4b",
        "color_text_title": "#4b4b4b"
      }
    },
    "5296c995-d215-4f33-b84c-516147ad69cb": {
      "type": "section-richtext",
      "settings": {
        "color_schema": "fifth_color",
        "button_round_off": false,
        "animation_setting": false,
        "padding_top": 4,
        "padding_bottom": 3,
        "banner_title_font_size": 45,
        "banner_font_size": 13,
        "headline": "About Our Featured Theme",
        "color_title": "#6f665d",
        "text": "<p>supports : love4stephanie@protonmail.com<\/p>",
        "color_desciption": "#6f665d",
        "textbox_align": "font_center",
        "button_size_first": "button_medium",
        "button-text": "",
        "button-url": "",
        "color_button": "second_color",
        "button_color_hover": "button_third_color",
        "border_color": "#6f665d",
        "button_size_second": "button_medium",
        "button-text_second": "",
        "button-url_second": "",
        "color_button_second": "second_color",
        "button_color_hover_second": "button_third_color",
        "border_color_second": "#6f665d"
      }
    },
    "1caebce1-a36d-47d8-954a-6c917078901e": {
      "type": "section-banner",
      "settings": {
        "image": "shopify:\/\/shop_images\/Screenshot_2022-10-06_230021.png",
        "img_array": "left_img",
        "animation_setting": true,
        "text_background": "second_color",
        "headline": "Navigation",
        "text_align": "banner_font_center",
        "text": "You can set Navigation colors, and control opacity. <br>  You can choose 3 kinds of navigation, submenu colors, and font colors too. You have to set mobile navigation separately.",
        "header_color": "#6f665d",
        "text_color": "#6f665d",
        "button_size": "button_medium",
        "button_round_off": false,
        "button-url": "",
        "button-text": "",
        "color_button": "second_color",
        "button_color_hover": "button_third_color",
        "border_color": "#6f665d"
      }
    },
    "ecbd86fd-a549-4c29-b79f-5529f2e87837": {
      "type": "section-banner",
      "settings": {
        "image": "shopify:\/\/shop_images\/Screenshot_2022-10-06_230147.png",
        "img_array": "right_img",
        "animation_setting": true,
        "text_background": "forth_color",
        "headline": "Mega menu",
        "text_align": "banner_font_center",
        "text": "You can set up two mega menus. The first one is a photo megamenu, and the second one is a regular mega menu. You have to type your link name, and set images and your custom product links.",
        "header_color": "#6f665d",
        "text_color": "#6f665d",
        "button_size": "button_medium",
        "button_round_off": false,
        "button-url": "",
        "button-text": "",
        "color_button": "second_color",
        "button_color_hover": "button_third_color",
        "border_color": "#6f665d"
      }
    },
    "4bb0c350-50cc-413e-a2ed-e8beb452b74b": {
      "type": "section-banner",
      "settings": {
        "image": "shopify:\/\/shop_images\/Screenshot_2022-10-07_000402.png",
        "img_array": "left_img",
        "animation_setting": true,
        "text_background": "second_color",
        "headline": "Photo Slideshow",
        "text_align": "banner_font_center",
        "text": "Photo slider makes your product collection more attractive. <br> Setting Photo and Collection slideshow to appeal to your special products.",
        "header_color": "#6f665d",
        "text_color": "#6f665d",
        "button_size": "button_medium",
        "button_round_off": false,
        "button-url": "",
        "button-text": "",
        "color_button": "second_color",
        "button_color_hover": "button_third_color",
        "border_color": "#6f665d"
      }
    },
    "b6249f90-f31f-4ef3-bd33-e3de90a45971": {
      "type": "section-banner",
      "settings": {
        "image": "shopify:\/\/shop_images\/Screenshot_2022-10-07_000548.png",
        "img_array": "right_img",
        "animation_setting": true,
        "text_background": "forth_color",
        "headline": "Animation",
        "text_align": "banner_font_center",
        "text": "You can turn on and off animation effects in every section. <br> You can find a checkbox to control animation scroll-down effects.",
        "header_color": "#6f665d",
        "text_color": "#6f665d",
        "button_size": "button_medium",
        "button_round_off": false,
        "button-url": "",
        "button-text": "",
        "color_button": "second_color",
        "button_color_hover": "button_third_color",
        "border_color": "#6f665d"
      }
    },
    "83b2a46b-4a4e-474a-8014-a33e9d8d86dd": {
      "type": "section-banner",
      "settings": {
        "image": "shopify:\/\/shop_images\/Screenshot_2022-10-06_235839.png",
        "img_array": "left_img",
        "animation_setting": true,
        "text_background": "third_color",
        "headline": "Merchandising",
        "text_align": "banner_font_center",
        "text": "Photo banners, variant options, and rich text, grid options help your product improvement. <br>Add your design sections on your blog, cart, and customer page too.<br> You can change your site which is your desired look.",
        "header_color": "#fafafa",
        "text_color": "#ffffff",
        "button_size": "button_medium",
        "button_round_off": false,
        "button-url": "",
        "button-text": "",
        "color_button": "second_color",
        "button_color_hover": "button_third_color",
        "border_color": "#6f665d"
      }
    }
  },
  "order": [
    "banner",
    "7df1c7f1-8d90-4871-b3ff-6a194669e723",
    "5296c995-d215-4f33-b84c-516147ad69cb",
    "1caebce1-a36d-47d8-954a-6c917078901e",
    "ecbd86fd-a549-4c29-b79f-5529f2e87837",
    "4bb0c350-50cc-413e-a2ed-e8beb452b74b",
    "b6249f90-f31f-4ef3-bd33-e3de90a45971",
    "83b2a46b-4a4e-474a-8014-a33e9d8d86dd"
  ]
}